{
  "aliasCount": 80,
  "aliases": [
    {
      "stars": 36150,
      "icon_url": "https://avatars.githubusercontent.com/u/1022859?v\u003d4",
      "repoOwner": "eugenp",
      "repoName": "tutorials",
      "alias": "hello",
      "scriptRef": "hello.java",
      "command": "hello@eugenp/tutorials~jbang",
      "fullcommand": "jbang hello@eugenp/tutorials~jbang",
      "link": "https://github.com/eugenp/tutorials/blob/8af8e7b145275847fcf808e9dd4311144997d922/jbang/jbang-catalog.json"
    },
    {
      "stars": 36150,
      "icon_url": "https://avatars.githubusercontent.com/u/1022859?v\u003d4",
      "repoOwner": "eugenp",
      "repoName": "tutorials",
      "alias": "hellocli",
      "scriptRef": "hellocli.java",
      "command": "hellocli@eugenp/tutorials~jbang",
      "fullcommand": "jbang hellocli@eugenp/tutorials~jbang",
      "link": "https://github.com/eugenp/tutorials/blob/8af8e7b145275847fcf808e9dd4311144997d922/jbang/jbang-catalog.json"
    },
    {
      "stars": 36150,
      "icon_url": "https://avatars.githubusercontent.com/u/1022859?v\u003d4",
      "repoOwner": "eugenp",
      "repoName": "tutorials",
      "alias": "jbangquarkus",
      "scriptRef": "jbangquarkus.java",
      "command": "jbangquarkus@eugenp/tutorials~jbang",
      "fullcommand": "jbang jbangquarkus@eugenp/tutorials~jbang",
      "link": "https://github.com/eugenp/tutorials/blob/8af8e7b145275847fcf808e9dd4311144997d922/jbang/jbang-catalog.json"
    },
    {
      "stars": 13239,
      "icon_url": "https://avatars.githubusercontent.com/u/47638783?v\u003d4",
      "repoOwner": "quarkusio",
      "repoName": "quarkus",
      "alias": "revapi-update",
      "scriptRef": "RevapiUpdate.java",
      "command": "revapi-update@quarkusio/quarkus~.jbang",
      "fullcommand": "jbang revapi-update@quarkusio/quarkus~.jbang",
      "link": "https://github.com/quarkusio/quarkus/blob/531e9e470124d813200f03a0c49eb97af04d9818/.jbang/jbang-catalog.json"
    },
    {
      "stars": 5369,
      "icon_url": "https://avatars.githubusercontent.com/u/47359?v\u003d4",
      "repoOwner": "apache",
      "repoName": "camel",
      "alias": "camel",
      "description": "\u003cp\u003eRun Apache Camel routes easily\u003c/p\u003e\n",
      "scriptRef": "dsl/camel-jbang/camel-jbang-main/dist/CamelJBang.java",
      "command": "camel@apache/camel",
      "fullcommand": "jbang camel@apache/camel",
      "link": "https://github.com/apache/camel/blob/4a4f78d43c89c42ed0f1ffe052cdabaff64298a2/jbang-catalog.json"
    },
    {
      "stars": 1756,
      "icon_url": "https://avatars.githubusercontent.com/u/8267906?v\u003d4",
      "repoOwner": "tabulapdf",
      "repoName": "tabula-java",
      "alias": "tabula",
      "scriptRef": "https://github.com/tabulapdf/tabula-java/releases/download/v1.0.4/tabula-1.0.4-jar-with-dependencies.jar",
      "command": "tabula@tabulapdf/tabula-java",
      "fullcommand": "jbang tabula@tabulapdf/tabula-java",
      "link": "https://github.com/tabulapdf/tabula-java/blob/8bfa3ad23af34f757f72fe46584a34abfc022ed3/jbang-catalog.json"
    },
    {
      "stars": 443,
      "icon_url": "https://avatars.githubusercontent.com/u/27848811?v\u003d4",
      "repoOwner": "citrusframework",
      "repoName": "citrus",
      "alias": "citrus",
      "description": "\u003cp\u003eRun Citrus tests\u003c/p\u003e\n",
      "scriptRef": "tools/jbang/dist/CitrusJBang.java",
      "command": "citrus@citrusframework/citrus",
      "fullcommand": "jbang citrus@citrusframework/citrus",
      "link": "https://github.com/citrusframework/citrus/blob/0b2cb618789925a86fa736484321980b4f1c112a/jbang-catalog.json"
    },
    {
      "stars": 123,
      "icon_url": "https://avatars.githubusercontent.com/u/26695883?v\u003d4",
      "repoOwner": "jvm-profiling-tools",
      "repoName": "ap-loader",
      "alias": "ap-loader",
      "description": "\u003cp\u003easync profiler loader. Use directly with \u003ccode\u003ejbang ap-loader@jvm-profiling-tools/ap-loader\u003c/code\u003e or use as agent with \u003ccode\u003ejbang --javaagent\u003dap-loader@jvm-profile-tools/ap-loader ...\u003c/code\u003e.\u003c/p\u003e\n",
      "scriptRef": "https://github.com/jvm-profiling-tools/ap-loader/releases/latest/download/ap-loader-all.jar",
      "command": "ap-loader@jvm-profiling-tools/ap-loader",
      "fullcommand": "jbang ap-loader@jvm-profiling-tools/ap-loader",
      "link": "https://github.com/jvm-profiling-tools/ap-loader/blob/ce29b5b6d4356dae914dc4fdb4fd418297c46c7a/jbang-catalog.json"
    },
    {
      "stars": 123,
      "icon_url": "https://avatars.githubusercontent.com/u/26695883?v\u003d4",
      "repoOwner": "jvm-profiling-tools",
      "repoName": "ap-loader",
      "alias": "jfr2nflx",
      "scriptRef": "https://github.com/jvm-profiling-tools/ap-loader/releases/latest/download/ap-loader-all.jar",
      "command": "jfr2nflx@jvm-profiling-tools/ap-loader",
      "fullcommand": "jbang jfr2nflx@jvm-profiling-tools/ap-loader",
      "link": "https://github.com/jvm-profiling-tools/ap-loader/blob/ce29b5b6d4356dae914dc4fdb4fd418297c46c7a/jbang-catalog.json"
    },
    {
      "stars": 123,
      "icon_url": "https://avatars.githubusercontent.com/u/26695883?v\u003d4",
      "repoOwner": "jvm-profiling-tools",
      "repoName": "ap-loader",
      "alias": "jfr2pprof",
      "scriptRef": "https://github.com/jvm-profiling-tools/ap-loader/releases/latest/download/ap-loader-all.jar",
      "command": "jfr2pprof@jvm-profiling-tools/ap-loader",
      "fullcommand": "jbang jfr2pprof@jvm-profiling-tools/ap-loader",
      "link": "https://github.com/jvm-profiling-tools/ap-loader/blob/ce29b5b6d4356dae914dc4fdb4fd418297c46c7a/jbang-catalog.json"
    },
    {
      "stars": 123,
      "icon_url": "https://avatars.githubusercontent.com/u/26695883?v\u003d4",
      "repoOwner": "jvm-profiling-tools",
      "repoName": "ap-loader",
      "alias": "jfr2flame",
      "scriptRef": "https://github.com/jvm-profiling-tools/ap-loader/releases/latest/download/ap-loader-all.jar",
      "command": "jfr2flame@jvm-profiling-tools/ap-loader",
      "fullcommand": "jbang jfr2flame@jvm-profiling-tools/ap-loader",
      "link": "https://github.com/jvm-profiling-tools/ap-loader/blob/ce29b5b6d4356dae914dc4fdb4fd418297c46c7a/jbang-catalog.json"
    },
    {
      "stars": 123,
      "icon_url": "https://avatars.githubusercontent.com/u/26695883?v\u003d4",
      "repoOwner": "jvm-profiling-tools",
      "repoName": "ap-loader",
      "alias": "converter",
      "scriptRef": "https://github.com/jvm-profiling-tools/ap-loader/releases/latest/download/ap-loader-all.jar",
      "command": "converter@jvm-profiling-tools/ap-loader",
      "fullcommand": "jbang converter@jvm-profiling-tools/ap-loader",
      "link": "https://github.com/jvm-profiling-tools/ap-loader/blob/ce29b5b6d4356dae914dc4fdb4fd418297c46c7a/jbang-catalog.json"
    },
    {
      "stars": 123,
      "icon_url": "https://avatars.githubusercontent.com/u/26695883?v\u003d4",
      "repoOwner": "jvm-profiling-tools",
      "repoName": "ap-loader",
      "alias": "profiler",
      "scriptRef": "ap-loader@jvm-profiling-tools/ap-loader",
      "command": "profiler@jvm-profiling-tools/ap-loader",
      "fullcommand": "jbang profiler@jvm-profiling-tools/ap-loader",
      "link": "https://github.com/jvm-profiling-tools/ap-loader/blob/ce29b5b6d4356dae914dc4fdb4fd418297c46c7a/jbang-catalog.json"
    },
    {
      "stars": 123,
      "icon_url": "https://avatars.githubusercontent.com/u/26695883?v\u003d4",
      "repoOwner": "jvm-profiling-tools",
      "repoName": "ap-loader",
      "alias": "jattach",
      "scriptRef": "ap-loader@jvm-profiling-tools/ap-loader",
      "command": "jattach@jvm-profiling-tools/ap-loader",
      "fullcommand": "jbang jattach@jvm-profiling-tools/ap-loader",
      "link": "https://github.com/jvm-profiling-tools/ap-loader/blob/ce29b5b6d4356dae914dc4fdb4fd418297c46c7a/jbang-catalog.json"
    },
    {
      "stars": 79,
      "icon_url": "https://avatars.githubusercontent.com/u/27848811?v\u003d4",
      "repoOwner": "citrusframework",
      "repoName": "yaks",
      "alias": "yaks",
      "description": "\u003cp\u003eRun YAKS tests locally\u003c/p\u003e\n",
      "scriptRef": "java/tools/yaks-jbang/dist/YaksJBang.java",
      "command": "yaks@citrusframework/yaks",
      "fullcommand": "jbang yaks@citrusframework/yaks",
      "link": "https://github.com/citrusframework/yaks/blob/05f61c494dfdd8a00346fcda547adf39ee960bcc/jbang-catalog.json"
    },
    {
      "stars": 45,
      "icon_url": "https://avatars.githubusercontent.com/u/877286?v\u003d4",
      "repoOwner": "manikmagar",
      "repoName": "mulefd",
      "alias": "mulefd",
      "description": "\u003cp\u003eRuns Mule Flow Diagrams\u003c/p\u003e\n",
      "scriptRef": "jbang/mulefd.java",
      "command": "mulefd@manikmagar/mulefd",
      "fullcommand": "jbang mulefd@manikmagar/mulefd",
      "link": "https://github.com/manikmagar/mulefd/blob/ca338602a6afbb18100bac41211d6c0d9a805ffa/jbang-catalog.json"
    },
    {
      "stars": 30,
      "icon_url": "https://avatars.githubusercontent.com/u/4993735?v\u003d4",
      "repoOwner": "ricksbrown",
      "repoName": "cowsay",
      "alias": "cowsay",
      "scriptRef": "com.github.ricksbrown:cowsay:LATEST",
      "command": "cowsay@ricksbrown/cowsay",
      "fullcommand": "jbang cowsay@ricksbrown/cowsay",
      "link": "https://github.com/ricksbrown/cowsay/blob/2ff80a5b98b4fe2af5a0e648bdf37a3769528ac3/jbang-catalog.json"
    },
    {
      "stars": 12,
      "icon_url": "https://avatars.githubusercontent.com/u/477100?v\u003d4",
      "repoOwner": "davsclaus",
      "repoName": "camel-visual",
      "alias": "launch",
      "scriptRef": "src/main/java/org/apache/camel/visual/VisualRouteMain.java",
      "command": "launch@davsclaus/camel-visual",
      "fullcommand": "jbang launch@davsclaus/camel-visual",
      "link": "https://github.com/davsclaus/camel-visual/blob/c2cb65b943091cff862b3bb4d95d18f4234a28ad/jbang-catalog.json"
    },
    {
      "stars": 7,
      "icon_url": "https://avatars.githubusercontent.com/u/1961952?v\u003d4",
      "repoOwner": "alibaba",
      "repoName": "jbang-catalog",
      "alias": "arthas",
      "description": "\u003cp\u003eLaunch Arthas Java Diagnostic Tool - \u003ca rel\u003d\"nofollow\" href\u003d\"https://github.com/alibaba/arthas\"\u003ehttps://github.com/alibaba/arthas\u003c/a\u003e\u003c/p\u003e\n",
      "scriptRef": "https://repo1.maven.org/maven2/com/taobao/arthas/arthas-boot/3.7.2/arthas-boot-3.7.2.jar",
      "command": "arthas@alibaba",
      "fullcommand": "jbang arthas@alibaba",
      "link": "https://github.com/alibaba/jbang-catalog/blob/87a97cf0dba31ad443660a58218704fa214fd7cf/jbang-catalog.json"
    },
    {
      "stars": 7,
      "icon_url": "https://avatars.githubusercontent.com/u/1961952?v\u003d4",
      "repoOwner": "alibaba",
      "repoName": "jbang-catalog",
      "alias": "rsocket-broker",
      "description": "\u003cp\u003eStart Alibaba RSocket Broker - \u003ca rel\u003d\"nofollow\" href\u003d\"https://github.com/alibaba/alibaba-rsocket-broker\"\u003ehttps://github.com/alibaba/alibaba-rsocket-broker\u003c/a\u003e\u003c/p\u003e\n",
      "scriptRef": "https://repo1.maven.org/maven2/com/alibaba/rsocket/alibaba-broker-server/1.1.6/alibaba-broker-server-1.1.6.jar",
      "command": "rsocket-broker@alibaba",
      "fullcommand": "jbang rsocket-broker@alibaba",
      "link": "https://github.com/alibaba/jbang-catalog/blob/87a97cf0dba31ad443660a58218704fa214fd7cf/jbang-catalog.json"
    },
    {
      "stars": 5,
      "icon_url": "https://avatars.githubusercontent.com/u/517980?v\u003d4",
      "repoOwner": "kiegroup",
      "repoName": "jbang-catalog",
      "alias": "dmn",
      "description": "\u003cp\u003eEvaluate a DMN model using the Drools DMN Engine.\u003c/p\u003e\n",
      "scriptRef": "dmn.java",
      "command": "dmn@kiegroup",
      "fullcommand": "jbang dmn@kiegroup",
      "link": "https://github.com/kiegroup/jbang-catalog/blob/addbd6476d11b26da5a9c0b0b4d47ad5b3a385e7/jbang-catalog.json"
    },
    {
      "stars": 5,
      "icon_url": "https://avatars.githubusercontent.com/u/517980?v\u003d4",
      "repoOwner": "kiegroup",
      "repoName": "jbang-catalog",
      "alias": "feel",
      "description": "\u003cp\u003eEvaluate a FEEL expression using the Drools DMN Engine.\u003c/p\u003e\n",
      "scriptRef": "feel.java",
      "command": "feel@kiegroup",
      "fullcommand": "jbang feel@kiegroup",
      "link": "https://github.com/kiegroup/jbang-catalog/blob/addbd6476d11b26da5a9c0b0b4d47ad5b3a385e7/jbang-catalog.json"
    },
    {
      "stars": 5,
      "icon_url": "https://avatars.githubusercontent.com/u/517980?v\u003d4",
      "repoOwner": "kiegroup",
      "repoName": "jbang-catalog",
      "alias": "optaplannerHelloWorld",
      "description": "\u003cp\u003eOptaPlanner Hello world to solve a school timetable to assign lessons to timeslots and rooms.\u003c/p\u003e\n",
      "scriptRef": "optaplannerHelloWorld.java",
      "command": "optaplannerHelloWorld@kiegroup",
      "fullcommand": "jbang optaplannerHelloWorld@kiegroup",
      "link": "https://github.com/kiegroup/jbang-catalog/blob/addbd6476d11b26da5a9c0b0b4d47ad5b3a385e7/jbang-catalog.json"
    },
    {
      "stars": 5,
      "icon_url": "https://avatars.githubusercontent.com/u/517980?v\u003d4",
      "repoOwner": "kiegroup",
      "repoName": "jbang-catalog",
      "alias": "xls2dmn",
      "description": "\u003cp\u003eJBang script proxy of the Converter for Excel (.xls/.xlsx) files containing DMN decision tables.\u003c/p\u003e\n",
      "scriptRef": "xls2dmn.java",
      "command": "xls2dmn@kiegroup",
      "fullcommand": "jbang xls2dmn@kiegroup",
      "link": "https://github.com/kiegroup/jbang-catalog/blob/addbd6476d11b26da5a9c0b0b4d47ad5b3a385e7/jbang-catalog.json"
    },
    {
      "stars": 2,
      "icon_url": "https://avatars.githubusercontent.com/u/778793?v\u003d4",
      "repoOwner": "quintesse",
      "repoName": "jbang-catalog",
      "alias": "cat",
      "description": "\u003cp\u003eSimply copies the contents of the provided files to the standard output\u003c/p\u003e\n",
      "scriptRef": "cat.java",
      "command": "cat@quintesse",
      "fullcommand": "jbang cat@quintesse",
      "link": "https://github.com/quintesse/jbang-catalog/blob/5f9de78fe388d84d86cc8a96680b29f4ce558df7/jbang-catalog.json"
    },
    {
      "stars": 2,
      "icon_url": "https://avatars.githubusercontent.com/u/778793?v\u003d4",
      "repoOwner": "quintesse",
      "repoName": "jbang-catalog",
      "alias": "echo",
      "description": "\u003cp\u003eJust prints out its arguments\u003c/p\u003e\n",
      "scriptRef": "echo.java",
      "command": "echo@quintesse",
      "fullcommand": "jbang echo@quintesse",
      "link": "https://github.com/quintesse/jbang-catalog/blob/5f9de78fe388d84d86cc8a96680b29f4ce558df7/jbang-catalog.json"
    },
    {
      "stars": 2,
      "icon_url": "https://avatars.githubusercontent.com/u/778793?v\u003d4",
      "repoOwner": "quintesse",
      "repoName": "jbang-catalog",
      "alias": "hello",
      "description": "\u003cp\u003eOur perennial demo friend\u003c/p\u003e\n",
      "scriptRef": "hello.java",
      "command": "hello@quintesse",
      "fullcommand": "jbang hello@quintesse",
      "link": "https://github.com/quintesse/jbang-catalog/blob/5f9de78fe388d84d86cc8a96680b29f4ce558df7/jbang-catalog.json"
    },
    {
      "stars": 2,
      "icon_url": "https://avatars.githubusercontent.com/u/778793?v\u003d4",
      "repoOwner": "quintesse",
      "repoName": "jbang-catalog",
      "alias": "jget",
      "description": "\u003cp\u003eLike a simplistic wget but written in Java\u003c/p\u003e\n",
      "scriptRef": "jget.java",
      "command": "jget@quintesse",
      "fullcommand": "jbang jget@quintesse",
      "link": "https://github.com/quintesse/jbang-catalog/blob/5f9de78fe388d84d86cc8a96680b29f4ce558df7/jbang-catalog.json"
    },
    {
      "stars": 2,
      "icon_url": "https://avatars.githubusercontent.com/u/778793?v\u003d4",
      "repoOwner": "quintesse",
      "repoName": "jbang-catalog",
      "alias": "jvmci",
      "description": "\u003cp\u003eChecks if JVMCI is enabled\u003c/p\u003e\n",
      "scriptRef": "jvmci.java",
      "command": "jvmci@quintesse",
      "fullcommand": "jbang jvmci@quintesse",
      "link": "https://github.com/quintesse/jbang-catalog/blob/5f9de78fe388d84d86cc8a96680b29f4ce558df7/jbang-catalog.json"
    },
    {
      "stars": 2,
      "icon_url": "https://avatars.githubusercontent.com/u/778793?v\u003d4",
      "repoOwner": "quintesse",
      "repoName": "jbang-catalog",
      "alias": "rest",
      "description": "\u003cp\u003eA cli tool for REST queries and transformations\u003c/p\u003e\n",
      "scriptRef": "rest.java",
      "command": "rest@quintesse",
      "fullcommand": "jbang rest@quintesse",
      "link": "https://github.com/quintesse/jbang-catalog/blob/5f9de78fe388d84d86cc8a96680b29f4ce558df7/jbang-catalog.json"
    },
    {
      "stars": 2,
      "icon_url": "https://avatars.githubusercontent.com/u/778793?v\u003d4",
      "repoOwner": "quintesse",
      "repoName": "jbang-catalog",
      "alias": "httpd",
      "description": "\u003cp\u003eStarts a simple HTTP server on the files in the current directory\u003c/p\u003e\n",
      "scriptRef": "simple_httpd.java",
      "command": "httpd@quintesse",
      "fullcommand": "jbang httpd@quintesse",
      "link": "https://github.com/quintesse/jbang-catalog/blob/5f9de78fe388d84d86cc8a96680b29f4ce558df7/jbang-catalog.json"
    },
    {
      "stars": 2,
      "icon_url": "https://avatars.githubusercontent.com/u/778793?v\u003d4",
      "repoOwner": "quintesse",
      "repoName": "jbang-catalog",
      "alias": "sysenv",
      "description": "\u003cp\u003ePrints out Java\u0027s System environment\u003c/p\u003e\n",
      "scriptRef": "system_env.java",
      "command": "sysenv@quintesse",
      "fullcommand": "jbang sysenv@quintesse",
      "link": "https://github.com/quintesse/jbang-catalog/blob/5f9de78fe388d84d86cc8a96680b29f4ce558df7/jbang-catalog.json"
    },
    {
      "stars": 2,
      "icon_url": "https://avatars.githubusercontent.com/u/778793?v\u003d4",
      "repoOwner": "quintesse",
      "repoName": "jbang-catalog",
      "alias": "sysprops",
      "description": "\u003cp\u003ePrints out Java\u0027s System properties\u003c/p\u003e\n",
      "scriptRef": "system_properties.java",
      "command": "sysprops@quintesse",
      "fullcommand": "jbang sysprops@quintesse",
      "link": "https://github.com/quintesse/jbang-catalog/blob/5f9de78fe388d84d86cc8a96680b29f4ce558df7/jbang-catalog.json"
    },
    {
      "stars": 2,
      "icon_url": "https://avatars.githubusercontent.com/u/778793?v\u003d4",
      "repoOwner": "quintesse",
      "repoName": "jbang-catalog",
      "alias": "mdns",
      "scriptRef": "mdns.java",
      "command": "mdns@quintesse",
      "fullcommand": "jbang mdns@quintesse",
      "link": "https://github.com/quintesse/jbang-catalog/blob/5f9de78fe388d84d86cc8a96680b29f4ce558df7/jbang-catalog.json"
    },
    {
      "stars": 2,
      "icon_url": "https://avatars.githubusercontent.com/u/3737888?v\u003d4",
      "repoOwner": "scratches",
      "repoName": "jbang-catalog",
      "alias": "spring",
      "description": "\u003cp\u003eSpring Boot CLI\u003c/p\u003e\n",
      "scriptRef": "org.springframework.boot:spring-boot-cli:2.4.5:full",
      "command": "spring@scratches",
      "fullcommand": "jbang spring@scratches",
      "link": "https://github.com/scratches/jbang-catalog/blob/80ff6d777253b30e70d41fad7f13bb70311b08a8/jbang-catalog.json"
    },
    {
      "stars": 2,
      "icon_url": "https://avatars.githubusercontent.com/u/3737888?v\u003d4",
      "repoOwner": "scratches",
      "repoName": "jbang-catalog",
      "alias": "configserver",
      "description": "\u003cp\u003eSpring Cloud Config Server with example config repo\u003c/p\u003e\n",
      "scriptRef": "ConfigServerApplication.java",
      "command": "configserver@scratches",
      "fullcommand": "jbang configserver@scratches",
      "link": "https://github.com/scratches/jbang-catalog/blob/80ff6d777253b30e70d41fad7f13bb70311b08a8/jbang-catalog.json"
    },
    {
      "stars": 2,
      "icon_url": "https://avatars.githubusercontent.com/u/8778468?v\u003d4",
      "repoOwner": "nbbrd",
      "repoName": "jbang-catalog",
      "alias": "hello-nbbrd",
      "description": "\u003cp\u003eHello NBBRD\u003c/p\u003e\n",
      "scriptRef": "hello_nbbrd.java",
      "command": "hello-nbbrd@nbbrd",
      "fullcommand": "jbang hello-nbbrd@nbbrd",
      "link": "https://github.com/nbbrd/jbang-catalog/blob/bfffa9baf233c4ee7cdc8b1e6b909d0805da9e65/jbang-catalog.json"
    },
    {
      "stars": 2,
      "icon_url": "https://avatars.githubusercontent.com/u/8778468?v\u003d4",
      "repoOwner": "nbbrd",
      "repoName": "jbang-catalog",
      "alias": "sdmx-dl",
      "description": "\u003cp\u003eEasily download official statistics\u003c/p\u003e\n",
      "scriptRef": "sdmx_dl.java",
      "command": "sdmx-dl@nbbrd",
      "fullcommand": "jbang sdmx-dl@nbbrd",
      "link": "https://github.com/nbbrd/jbang-catalog/blob/bfffa9baf233c4ee7cdc8b1e6b909d0805da9e65/jbang-catalog.json"
    },
    {
      "stars": 2,
      "icon_url": "https://avatars.githubusercontent.com/u/8778468?v\u003d4",
      "repoOwner": "nbbrd",
      "repoName": "jbang-catalog",
      "alias": "heylogs",
      "description": "\u003cp\u003eKeep-a-changelog tool\u003c/p\u003e\n",
      "scriptRef": "heylogs.java",
      "command": "heylogs@nbbrd",
      "fullcommand": "jbang heylogs@nbbrd",
      "link": "https://github.com/nbbrd/jbang-catalog/blob/bfffa9baf233c4ee7cdc8b1e6b909d0805da9e65/jbang-catalog.json"
    },
    {
      "stars": 2,
      "icon_url": "https://avatars.githubusercontent.com/u/8778468?v\u003d4",
      "repoOwner": "nbbrd",
      "repoName": "jbang-catalog",
      "alias": "hello-nbbrd-picocli",
      "description": "\u003cp\u003eHello NBBRD\u003c/p\u003e\n",
      "scriptRef": "hello_nbbrd_picocli.java",
      "command": "hello-nbbrd-picocli@nbbrd",
      "fullcommand": "jbang hello-nbbrd-picocli@nbbrd",
      "link": "https://github.com/nbbrd/jbang-catalog/blob/bfffa9baf233c4ee7cdc8b1e6b909d0805da9e65/jbang-catalog.json"
    },
    {
      "stars": 1,
      "icon_url": "https://avatars.githubusercontent.com/u/81020166?v\u003d4",
      "repoOwner": "jreleaser",
      "repoName": "jbang-catalog",
      "alias": "jreleaser",
      "description": "\u003cp\u003eRelease projects quickly and easily with JReleaser\u003c/p\u003e\n",
      "scriptRef": "jreleaser.java",
      "command": "jreleaser@jreleaser",
      "fullcommand": "jbang jreleaser@jreleaser",
      "link": "https://github.com/jreleaser/jbang-catalog/blob/bc13ec097dc7920b3bdb7008e05d9985393c1d44/jbang-catalog.json"
    },
    {
      "stars": 1,
      "icon_url": "https://avatars.githubusercontent.com/u/81020166?v\u003d4",
      "repoOwner": "jreleaser",
      "repoName": "jbang-catalog",
      "alias": "jreleaser-snapshot",
      "description": "\u003cp\u003eRelease projects quickly and easily with JReleaser\u003c/p\u003e\n",
      "scriptRef": "jreleaser_snapshot.java",
      "command": "jreleaser-snapshot@jreleaser",
      "fullcommand": "jbang jreleaser-snapshot@jreleaser",
      "link": "https://github.com/jreleaser/jbang-catalog/blob/bc13ec097dc7920b3bdb7008e05d9985393c1d44/jbang-catalog.json"
    },
    {
      "stars": 1,
      "icon_url": "https://avatars.githubusercontent.com/u/54129?v\u003d4",
      "repoOwner": "maxandersen",
      "repoName": "xam.dk",
      "alias": "tree",
      "scriptRef": "tree/main.java",
      "command": "tree@maxandersen/xam.dk",
      "fullcommand": "jbang tree@maxandersen/xam.dk",
      "link": "https://github.com/maxandersen/xam.dk/blob/3649654358d35a2d29ae734e301673a37b6ffb55/jbang-catalog.json"
    },
    {
      "stars": 1,
      "icon_url": "https://avatars.githubusercontent.com/u/54129?v\u003d4",
      "repoOwner": "maxandersen",
      "repoName": "xam.dk",
      "alias": "qrcode",
      "scriptRef": "qrcode/main.java",
      "command": "qrcode@maxandersen/xam.dk",
      "fullcommand": "jbang qrcode@maxandersen/xam.dk",
      "link": "https://github.com/maxandersen/xam.dk/blob/3649654358d35a2d29ae734e301673a37b6ffb55/jbang-catalog.json"
    },
    {
      "stars": 1,
      "icon_url": "https://avatars.githubusercontent.com/u/1939631?v\u003d4",
      "repoOwner": "jacoco",
      "repoName": "jbang-catalog",
      "alias": "cli",
      "description": "\u003cp\u003eRuns jacoco cli, see \u003ca rel\u003d\"nofollow\" href\u003d\"https://www.jacoco.org/jacoco/trunk/doc/cli.html\"\u003ehttps://www.jacoco.org/jacoco/trunk/doc/cli.html\u003c/a\u003e for documentation.\u003c/p\u003e\n",
      "scriptRef": "org.jacoco:org.jacoco.cli:RELEASE:nodeps",
      "command": "cli@jacoco",
      "fullcommand": "jbang cli@jacoco",
      "link": "https://github.com/jacoco/jbang-catalog/blob/678e949a1f87fcb1c92f0f781921e1290bc3ebde/jbang-catalog.json"
    },
    {
      "stars": 1,
      "icon_url": "https://avatars.githubusercontent.com/u/1939631?v\u003d4",
      "repoOwner": "jacoco",
      "repoName": "jbang-catalog",
      "alias": "agent",
      "description": "\u003cp\u003ejacoco agent, use like \u003ccode\u003ejbang --javaagent \u0026lt;script\u0026gt;\u003c/code\u003e\u003c/p\u003e\n",
      "scriptRef": "org.jacoco:org.jacoco.agent:RELEASE:runtime",
      "command": "agent@jacoco",
      "fullcommand": "jbang agent@jacoco",
      "link": "https://github.com/jacoco/jbang-catalog/blob/678e949a1f87fcb1c92f0f781921e1290bc3ebde/jbang-catalog.json"
    },
    {
      "stars": 0,
      "icon_url": "https://avatars.githubusercontent.com/u/921666?v\u003d4",
      "repoOwner": "jlengrand",
      "repoName": "jbang-catalog",
      "alias": "app-snapshot",
      "description": "\u003cp\u003ehelidon-quickstart-se\u003c/p\u003e\n",
      "scriptRef": "app_snapshot.java",
      "command": "app-snapshot@jlengrand",
      "fullcommand": "jbang app-snapshot@jlengrand",
      "link": "https://github.com/jlengrand/jbang-catalog/blob/20a69fcc6aa072afa05c23ca478693ccf367b382/jbang-catalog.json"
    },
    {
      "stars": 0,
      "icon_url": "https://avatars.githubusercontent.com/u/921666?v\u003d4",
      "repoOwner": "jlengrand",
      "repoName": "jbang-catalog",
      "alias": "helidon-quickstart-se-snapshot",
      "description": "\u003cp\u003ehelidon-quickstart-se\u003c/p\u003e\n",
      "scriptRef": "helidon_quickstart_se_snapshot.java",
      "command": "helidon-quickstart-se-snapshot@jlengrand",
      "fullcommand": "jbang helidon-quickstart-se-snapshot@jlengrand",
      "link": "https://github.com/jlengrand/jbang-catalog/blob/20a69fcc6aa072afa05c23ca478693ccf367b382/jbang-catalog.json"
    },
    {
      "stars": 0,
      "icon_url": "https://avatars.githubusercontent.com/u/179265?v\u003d4",
      "repoOwner": "FroMage",
      "repoName": "jbang-catalog",
      "alias": "static-init-finder",
      "description": "\u003cp\u003eFind static init calls to classes\u003c/p\u003e\n",
      "scriptRef": "ListStaticInit.java",
      "command": "static-init-finder@FroMage",
      "fullcommand": "jbang static-init-finder@FroMage",
      "link": "https://github.com/FroMage/jbang-catalog/blob/88e67d933086e70879a32462c90e822cc8037051/jbang-catalog.json"
    },
    {
      "stars": 0,
      "icon_url": "https://avatars.githubusercontent.com/u/82864904?v\u003d4",
      "repoOwner": "rohankumardubey",
      "repoName": "karate-core",
      "alias": "karate",
      "scriptRef": "com.intuit.karate:karate-core:1.2.0:all",
      "command": "karate@rohankumardubey/karate-core",
      "fullcommand": "jbang karate@rohankumardubey/karate-core",
      "link": "https://github.com/rohankumardubey/karate-core/blob/3b4de72abf93431d8c9fc9301d806c6b931df004/jbang-catalog.json"
    },
    {
      "stars": 0,
      "icon_url": "https://avatars.githubusercontent.com/u/27861160?v\u003d4",
      "repoOwner": "gomezrondon",
      "repoName": "spring-in-container",
      "alias": "cleanyaml",
      "scriptRef": "jscript.java",
      "command": "cleanyaml@gomezrondon/spring-in-container~script",
      "fullcommand": "jbang cleanyaml@gomezrondon/spring-in-container~script",
      "link": "https://github.com/gomezrondon/spring-in-container/blob/546df82c9b5bd1159c9866101c79a2fd5d3b1388/script/jbang-catalog.json"
    },
    {
      "stars": 0,
      "icon_url": "https://avatars.githubusercontent.com/u/59115480?v\u003d4",
      "repoOwner": "kordamp",
      "repoName": "jbang-catalog",
      "alias": "pomchecker",
      "description": "\u003cp\u003eChecks POM files may be uploaded to Maven Central\u003c/p\u003e\n",
      "scriptRef": "pomchecker.java",
      "command": "pomchecker@kordamp",
      "fullcommand": "jbang pomchecker@kordamp",
      "link": "https://github.com/kordamp/jbang-catalog/blob/210ef095dbc3c8664bc44328ad11e97aaa74ba4b/jbang-catalog.json"
    },
    {
      "stars": 0,
      "icon_url": "https://avatars.githubusercontent.com/u/59115480?v\u003d4",
      "repoOwner": "kordamp",
      "repoName": "jbang-catalog",
      "alias": "pomchecker-snapshot",
      "description": "\u003cp\u003eChecks POM files may be uploaded to Maven Central\u003c/p\u003e\n",
      "scriptRef": "pomchecker_snapshot.java",
      "command": "pomchecker-snapshot@kordamp",
      "fullcommand": "jbang pomchecker-snapshot@kordamp",
      "link": "https://github.com/kordamp/jbang-catalog/blob/210ef095dbc3c8664bc44328ad11e97aaa74ba4b/jbang-catalog.json"
    },
    {
      "stars": 0,
      "icon_url": "https://avatars.githubusercontent.com/u/59115480?v\u003d4",
      "repoOwner": "kordamp",
      "repoName": "jbang-catalog",
      "alias": "jarviz-snapshot",
      "description": "\u003cp\u003eJAR file analyzer\u003c/p\u003e\n",
      "scriptRef": "jarviz_snapshot.java",
      "command": "jarviz-snapshot@kordamp",
      "fullcommand": "jbang jarviz-snapshot@kordamp",
      "link": "https://github.com/kordamp/jbang-catalog/blob/210ef095dbc3c8664bc44328ad11e97aaa74ba4b/jbang-catalog.json"
    },
    {
      "stars": 0,
      "icon_url": "https://avatars.githubusercontent.com/u/59115480?v\u003d4",
      "repoOwner": "kordamp",
      "repoName": "jbang-catalog",
      "alias": "jarviz",
      "description": "\u003cp\u003eJAR file analyzer\u003c/p\u003e\n",
      "scriptRef": "jarviz.java",
      "command": "jarviz@kordamp",
      "fullcommand": "jbang jarviz@kordamp",
      "link": "https://github.com/kordamp/jbang-catalog/blob/210ef095dbc3c8664bc44328ad11e97aaa74ba4b/jbang-catalog.json"
    },
    {
      "stars": 0,
      "icon_url": "https://avatars.githubusercontent.com/u/59115480?v\u003d4",
      "repoOwner": "kordamp",
      "repoName": "jbang-catalog",
      "alias": "naum-snapshot",
      "description": "\u003cp\u003eJava binary compatibility checking tool\u003c/p\u003e\n",
      "scriptRef": "naum_snapshot.java",
      "command": "naum-snapshot@kordamp",
      "fullcommand": "jbang naum-snapshot@kordamp",
      "link": "https://github.com/kordamp/jbang-catalog/blob/210ef095dbc3c8664bc44328ad11e97aaa74ba4b/jbang-catalog.json"
    },
    {
      "stars": 0,
      "icon_url": "https://avatars.githubusercontent.com/u/40258585?v\u003d4",
      "repoOwner": "DependencyTrack",
      "repoName": "jbang-catalog",
      "alias": "gen-config-docs",
      "description": "\u003cp\u003eGenerate configuration documentation from application.properties\u003c/p\u003e\n",
      "scriptRef": "GenerateConfigDocs.java",
      "command": "gen-config-docs@DependencyTrack",
      "fullcommand": "jbang gen-config-docs@DependencyTrack",
      "link": "https://github.com/DependencyTrack/jbang-catalog/blob/2ac0971f6c63972a33dde8a2cd06f7c42259c744/jbang-catalog.json"
    },
    {
      "stars": 0,
      "icon_url": "https://avatars.githubusercontent.com/u/40258585?v\u003d4",
      "repoOwner": "DependencyTrack",
      "repoName": "jbang-catalog",
      "alias": "gen-cwe-dict",
      "description": "\u003cp\u003eGenerate a Java class holding a dictionary of CWE ID -\u0026gt; CWE Name mappings\u003c/p\u003e\n",
      "scriptRef": "GenerateCweDictionary.java",
      "command": "gen-cwe-dict@DependencyTrack",
      "fullcommand": "jbang gen-cwe-dict@DependencyTrack",
      "link": "https://github.com/DependencyTrack/jbang-catalog/blob/2ac0971f6c63972a33dde8a2cd06f7c42259c744/jbang-catalog.json"
    },
    {
      "stars": 0,
      "icon_url": "https://avatars.githubusercontent.com/u/874086?v\u003d4",
      "repoOwner": "junit-team",
      "repoName": "jbang-catalog",
      "alias": "cli",
      "description": "\u003cp\u003eLaunch the JUnit Platform from the console\u003c/p\u003e\n",
      "scriptRef": "org.junit.platform:junit-platform-console-standalone:1.10.2",
      "command": "cli@junit-team",
      "fullcommand": "jbang cli@junit-team",
      "link": "https://github.com/junit-team/jbang-catalog/blob/c511ed8b7c1090dab7997fd8a12fcaf9fa07689f/jbang-catalog.json"
    },
    {
      "stars": 0,
      "icon_url": "https://avatars.githubusercontent.com/u/874086?v\u003d4",
      "repoOwner": "junit-team",
      "repoName": "jbang-catalog",
      "alias": "cli-1.10.2",
      "description": "\u003cp\u003eLaunch the JUnit Platform from the console\u003c/p\u003e\n",
      "scriptRef": "org.junit.platform:junit-platform-console-standalone:1.10.2",
      "command": "cli-1.10.2@junit-team",
      "fullcommand": "jbang cli-1.10.2@junit-team",
      "link": "https://github.com/junit-team/jbang-catalog/blob/c511ed8b7c1090dab7997fd8a12fcaf9fa07689f/jbang-catalog.json"
    },
    {
      "stars": 0,
      "icon_url": "https://avatars.githubusercontent.com/u/874086?v\u003d4",
      "repoOwner": "junit-team",
      "repoName": "jbang-catalog",
      "alias": "cli-1.10.1",
      "description": "\u003cp\u003eLaunch the JUnit Platform from the console\u003c/p\u003e\n",
      "scriptRef": "org.junit.platform:junit-platform-console-standalone:1.10.1",
      "command": "cli-1.10.1@junit-team",
      "fullcommand": "jbang cli-1.10.1@junit-team",
      "link": "https://github.com/junit-team/jbang-catalog/blob/c511ed8b7c1090dab7997fd8a12fcaf9fa07689f/jbang-catalog.json"
    },
    {
      "stars": 0,
      "icon_url": "https://avatars.githubusercontent.com/u/874086?v\u003d4",
      "repoOwner": "junit-team",
      "repoName": "jbang-catalog",
      "alias": "cli-1.10.0",
      "description": "\u003cp\u003eLaunch the JUnit Platform from the console\u003c/p\u003e\n",
      "scriptRef": "org.junit.platform:junit-platform-console-standalone:1.10.0",
      "command": "cli-1.10.0@junit-team",
      "fullcommand": "jbang cli-1.10.0@junit-team",
      "link": "https://github.com/junit-team/jbang-catalog/blob/c511ed8b7c1090dab7997fd8a12fcaf9fa07689f/jbang-catalog.json"
    },
    {
      "stars": 0,
      "icon_url": "https://avatars.githubusercontent.com/u/874086?v\u003d4",
      "repoOwner": "junit-team",
      "repoName": "jbang-catalog",
      "alias": "cli-1.9.3",
      "description": "\u003cp\u003eLaunch the JUnit Platform from the console\u003c/p\u003e\n",
      "scriptRef": "org.junit.platform:junit-platform-console-standalone:1.9.3",
      "command": "cli-1.9.3@junit-team",
      "fullcommand": "jbang cli-1.9.3@junit-team",
      "link": "https://github.com/junit-team/jbang-catalog/blob/c511ed8b7c1090dab7997fd8a12fcaf9fa07689f/jbang-catalog.json"
    },
    {
      "stars": 0,
      "icon_url": "https://avatars.githubusercontent.com/u/874086?v\u003d4",
      "repoOwner": "junit-team",
      "repoName": "jbang-catalog",
      "alias": "cli-1.9.2",
      "description": "\u003cp\u003eLaunch the JUnit Platform from the console\u003c/p\u003e\n",
      "scriptRef": "org.junit.platform:junit-platform-console-standalone:1.9.2",
      "command": "cli-1.9.2@junit-team",
      "fullcommand": "jbang cli-1.9.2@junit-team",
      "link": "https://github.com/junit-team/jbang-catalog/blob/c511ed8b7c1090dab7997fd8a12fcaf9fa07689f/jbang-catalog.json"
    },
    {
      "stars": 0,
      "icon_url": "https://avatars.githubusercontent.com/u/874086?v\u003d4",
      "repoOwner": "junit-team",
      "repoName": "jbang-catalog",
      "alias": "cli-1.9.1",
      "description": "\u003cp\u003eLaunch the JUnit Platform from the console\u003c/p\u003e\n",
      "scriptRef": "org.junit.platform:junit-platform-console-standalone:1.9.1",
      "command": "cli-1.9.1@junit-team",
      "fullcommand": "jbang cli-1.9.1@junit-team",
      "link": "https://github.com/junit-team/jbang-catalog/blob/c511ed8b7c1090dab7997fd8a12fcaf9fa07689f/jbang-catalog.json"
    },
    {
      "stars": 0,
      "icon_url": "https://avatars.githubusercontent.com/u/874086?v\u003d4",
      "repoOwner": "junit-team",
      "repoName": "jbang-catalog",
      "alias": "cli-1.9.0",
      "description": "\u003cp\u003eLaunch the JUnit Platform from the console\u003c/p\u003e\n",
      "scriptRef": "org.junit.platform:junit-platform-console-standalone:1.9.0",
      "command": "cli-1.9.0@junit-team",
      "fullcommand": "jbang cli-1.9.0@junit-team",
      "link": "https://github.com/junit-team/jbang-catalog/blob/c511ed8b7c1090dab7997fd8a12fcaf9fa07689f/jbang-catalog.json"
    },
    {
      "stars": 0,
      "icon_url": "https://avatars.githubusercontent.com/u/874086?v\u003d4",
      "repoOwner": "junit-team",
      "repoName": "jbang-catalog",
      "alias": "cli-1.8.2",
      "description": "\u003cp\u003eLaunch the JUnit Platform from the console\u003c/p\u003e\n",
      "scriptRef": "org.junit.platform:junit-platform-console-standalone:1.8.2",
      "command": "cli-1.8.2@junit-team",
      "fullcommand": "jbang cli-1.8.2@junit-team",
      "link": "https://github.com/junit-team/jbang-catalog/blob/c511ed8b7c1090dab7997fd8a12fcaf9fa07689f/jbang-catalog.json"
    },
    {
      "stars": 0,
      "icon_url": "https://avatars.githubusercontent.com/u/874086?v\u003d4",
      "repoOwner": "junit-team",
      "repoName": "jbang-catalog",
      "alias": "cli-1.8.1",
      "description": "\u003cp\u003eLaunch the JUnit Platform from the console\u003c/p\u003e\n",
      "scriptRef": "org.junit.platform:junit-platform-console-standalone:1.8.1",
      "command": "cli-1.8.1@junit-team",
      "fullcommand": "jbang cli-1.8.1@junit-team",
      "link": "https://github.com/junit-team/jbang-catalog/blob/c511ed8b7c1090dab7997fd8a12fcaf9fa07689f/jbang-catalog.json"
    },
    {
      "stars": 0,
      "icon_url": "https://avatars.githubusercontent.com/u/27719?v\u003d4",
      "repoOwner": "jianglibo",
      "repoName": "jbang-catalog",
      "alias": "html",
      "description": "\u003cp\u003edo html boilerplate staff\u003c/p\u003e\n",
      "scriptRef": "html/html.java",
      "command": "html@jianglibo",
      "fullcommand": "jbang html@jianglibo",
      "link": "https://github.com/jianglibo/jbang-catalog/blob/9ea753070a3e4713a55a3f9bd63e86a9b67b9447/jbang-catalog.json"
    },
    {
      "stars": 0,
      "icon_url": "https://avatars.githubusercontent.com/u/27719?v\u003d4",
      "repoOwner": "jianglibo",
      "repoName": "jbang-catalog",
      "alias": "rollup",
      "description": "\u003cp\u003eSetup a simple rollup project.\u003c/p\u003e\n",
      "scriptRef": "rollup/rollup.java",
      "command": "rollup@jianglibo",
      "fullcommand": "jbang rollup@jianglibo",
      "link": "https://github.com/jianglibo/jbang-catalog/blob/9ea753070a3e4713a55a3f9bd63e86a9b67b9447/jbang-catalog.json"
    },
    {
      "stars": 0,
      "icon_url": "https://avatars.githubusercontent.com/u/27719?v\u003d4",
      "repoOwner": "jianglibo",
      "repoName": "jbang-catalog",
      "alias": "lxcinfo",
      "description": "\u003cp\u003elxc interface.\u003c/p\u003e\n",
      "scriptRef": "lxcinfo/lxcinfo.java",
      "command": "lxcinfo@jianglibo",
      "fullcommand": "jbang lxcinfo@jianglibo",
      "link": "https://github.com/jianglibo/jbang-catalog/blob/9ea753070a3e4713a55a3f9bd63e86a9b67b9447/jbang-catalog.json"
    },
    {
      "stars": 0,
      "icon_url": "https://avatars.githubusercontent.com/u/27719?v\u003d4",
      "repoOwner": "jianglibo",
      "repoName": "jbang-catalog",
      "alias": "text",
      "description": "\u003cp\u003etext manipulation util\u003c/p\u003e\n",
      "scriptRef": "text/text.java",
      "command": "text@jianglibo",
      "fullcommand": "jbang text@jianglibo",
      "link": "https://github.com/jianglibo/jbang-catalog/blob/9ea753070a3e4713a55a3f9bd63e86a9b67b9447/jbang-catalog.json"
    },
    {
      "stars": 0,
      "icon_url": "https://avatars.githubusercontent.com/u/27719?v\u003d4",
      "repoOwner": "jianglibo",
      "repoName": "jbang-catalog",
      "alias": "snapshot",
      "description": "\u003cp\u003etake snapshot of the current project.\u003c/p\u003e\n",
      "scriptRef": "snapshot/snapshot.java",
      "command": "snapshot@jianglibo",
      "fullcommand": "jbang snapshot@jianglibo",
      "link": "https://github.com/jianglibo/jbang-catalog/blob/9ea753070a3e4713a55a3f9bd63e86a9b67b9447/jbang-catalog.json"
    },
    {
      "stars": 0,
      "icon_url": "https://avatars.githubusercontent.com/u/27719?v\u003d4",
      "repoOwner": "jianglibo",
      "repoName": "jbang-catalog",
      "alias": "command",
      "description": "\u003cp\u003emanage the user defined commands.\u003c/p\u003e\n",
      "scriptRef": "command/command.java",
      "command": "command@jianglibo",
      "fullcommand": "jbang command@jianglibo",
      "link": "https://github.com/jianglibo/jbang-catalog/blob/9ea753070a3e4713a55a3f9bd63e86a9b67b9447/jbang-catalog.json"
    },
    {
      "stars": 0,
      "icon_url": "https://avatars.githubusercontent.com/u/27719?v\u003d4",
      "repoOwner": "jianglibo",
      "repoName": "jbang-catalog",
      "alias": "download",
      "description": "\u003cp\u003edownload assets from this project.\u003c/p\u003e\n",
      "scriptRef": "download/download.java",
      "command": "download@jianglibo",
      "fullcommand": "jbang download@jianglibo",
      "link": "https://github.com/jianglibo/jbang-catalog/blob/9ea753070a3e4713a55a3f9bd63e86a9b67b9447/jbang-catalog.json"
    },
    {
      "stars": 0,
      "icon_url": "https://avatars.githubusercontent.com/u/27719?v\u003d4",
      "repoOwner": "jianglibo",
      "repoName": "jbang-catalog",
      "alias": "neovim",
      "description": "\u003cp\u003ea neovim ide.\u003c/p\u003e\n",
      "scriptRef": "neovim/neovim.java",
      "command": "neovim@jianglibo",
      "fullcommand": "jbang neovim@jianglibo",
      "link": "https://github.com/jianglibo/jbang-catalog/blob/9ea753070a3e4713a55a3f9bd63e86a9b67b9447/jbang-catalog.json"
    },
    {
      "stars": 0,
      "icon_url": "https://avatars.githubusercontent.com/u/27719?v\u003d4",
      "repoOwner": "jianglibo",
      "repoName": "jbang-catalog",
      "alias": "crypt",
      "description": "\u003cp\u003ea crypt utility\u003c/p\u003e\n",
      "scriptRef": "crypt/crypt.java",
      "command": "crypt@jianglibo",
      "fullcommand": "jbang crypt@jianglibo",
      "link": "https://github.com/jianglibo/jbang-catalog/blob/9ea753070a3e4713a55a3f9bd63e86a9b67b9447/jbang-catalog.json"
    },
    {
      "stars": 0,
      "icon_url": "https://avatars.githubusercontent.com/u/27719?v\u003d4",
      "repoOwner": "jianglibo",
      "repoName": "jbang-catalog",
      "alias": "runenv",
      "description": "\u003cp\u003emanage runenvs.\u003c/p\u003e\n",
      "scriptRef": "runenv/runenv.java",
      "command": "runenv@jianglibo",
      "fullcommand": "jbang runenv@jianglibo",
      "link": "https://github.com/jianglibo/jbang-catalog/blob/9ea753070a3e4713a55a3f9bd63e86a9b67b9447/jbang-catalog.json"
    },
    {
      "stars": 0,
      "icon_url": "https://avatars.githubusercontent.com/u/27719?v\u003d4",
      "repoOwner": "jianglibo",
      "repoName": "jbang-catalog",
      "alias": "h2",
      "scriptRef": "com.h2database:h2:1.4.200",
      "command": "h2@jianglibo",
      "fullcommand": "jbang h2@jianglibo",
      "link": "https://github.com/jianglibo/jbang-catalog/blob/9ea753070a3e4713a55a3f9bd63e86a9b67b9447/jbang-catalog.json"
    },
    {
      "stars": 0,
      "icon_url": "https://avatars.githubusercontent.com/u/27719?v\u003d4",
      "repoOwner": "jianglibo",
      "repoName": "jbang-catalog",
      "alias": "catalog2readme",
      "scriptRef": "catalog2readme.java",
      "command": "catalog2readme@jianglibo",
      "fullcommand": "jbang catalog2readme@jianglibo",
      "link": "https://github.com/jianglibo/jbang-catalog/blob/9ea753070a3e4713a55a3f9bd63e86a9b67b9447/jbang-catalog.json"
    }
  ],
  "templates": [
    {
      "stars": 1357,
      "icon_url": "https://avatars.githubusercontent.com/u/60074102?v\u003d4",
      "repoOwner": "jbangdev",
      "repoName": "jbang",
      "alias": "gpt",
      "description": "\u003cp\u003eTemplate using ChatGPT (requires --preview and OPENAI_API_KEY)\u003c/p\u003e\n",
      "command": "gpt@jbangdev/jbang~src/main/resources",
      "fullcommand": "jbang init -t gpt@jbangdev/jbang~src/main/resources",
      "link": "https://github.com/jbangdev/jbang/blob/d863c332d0ff207ef3a88039e701cda09cc54302/src/main/resources/jbang-catalog.json"
    },
    {
      "stars": 1357,
      "icon_url": "https://avatars.githubusercontent.com/u/60074102?v\u003d4",
      "repoOwner": "jbangdev",
      "repoName": "jbang",
      "alias": "gpt.kt",
      "description": "\u003cp\u003eTemplate using ChatGPT for kotlin (requires --preview and OPENAI_API_KEY)\u003c/p\u003e\n",
      "command": "gpt.kt@jbangdev/jbang~src/main/resources",
      "fullcommand": "jbang init -t gpt.kt@jbangdev/jbang~src/main/resources",
      "link": "https://github.com/jbangdev/jbang/blob/d863c332d0ff207ef3a88039e701cda09cc54302/src/main/resources/jbang-catalog.json"
    },
    {
      "stars": 1357,
      "icon_url": "https://avatars.githubusercontent.com/u/60074102?v\u003d4",
      "repoOwner": "jbangdev",
      "repoName": "jbang",
      "alias": "gpt.groovy",
      "description": "\u003cp\u003eTemplate using ChatGPT for groovy (requires --preview and OPENAI_API_KEY)\u003c/p\u003e\n",
      "command": "gpt.groovy@jbangdev/jbang~src/main/resources",
      "fullcommand": "jbang init -t gpt.groovy@jbangdev/jbang~src/main/resources",
      "link": "https://github.com/jbangdev/jbang/blob/d863c332d0ff207ef3a88039e701cda09cc54302/src/main/resources/jbang-catalog.json"
    },
    {
      "stars": 1357,
      "icon_url": "https://avatars.githubusercontent.com/u/60074102?v\u003d4",
      "repoOwner": "jbangdev",
      "repoName": "jbang",
      "alias": "agent",
      "description": "\u003cp\u003eAgent template\u003c/p\u003e\n",
      "command": "agent@jbangdev/jbang~src/main/resources",
      "fullcommand": "jbang init -t agent@jbangdev/jbang~src/main/resources",
      "link": "https://github.com/jbangdev/jbang/blob/d863c332d0ff207ef3a88039e701cda09cc54302/src/main/resources/jbang-catalog.json"
    },
    {
      "stars": 1357,
      "icon_url": "https://avatars.githubusercontent.com/u/60074102?v\u003d4",
      "repoOwner": "jbangdev",
      "repoName": "jbang",
      "alias": "cli",
      "description": "\u003cp\u003eCLI template\u003c/p\u003e\n",
      "command": "cli@jbangdev/jbang~src/main/resources",
      "fullcommand": "jbang init -t cli@jbangdev/jbang~src/main/resources",
      "link": "https://github.com/jbangdev/jbang/blob/d863c332d0ff207ef3a88039e701cda09cc54302/src/main/resources/jbang-catalog.json"
    },
    {
      "stars": 1357,
      "icon_url": "https://avatars.githubusercontent.com/u/60074102?v\u003d4",
      "repoOwner": "jbangdev",
      "repoName": "jbang",
      "alias": "hello",
      "description": "\u003cp\u003eBasic Hello World template\u003c/p\u003e\n",
      "command": "hello@jbangdev/jbang~src/main/resources",
      "fullcommand": "jbang init -t hello@jbangdev/jbang~src/main/resources",
      "link": "https://github.com/jbangdev/jbang/blob/d863c332d0ff207ef3a88039e701cda09cc54302/src/main/resources/jbang-catalog.json"
    },
    {
      "stars": 1357,
      "icon_url": "https://avatars.githubusercontent.com/u/60074102?v\u003d4",
      "repoOwner": "jbangdev",
      "repoName": "jbang",
      "alias": "hello.kt",
      "description": "\u003cp\u003eBasic kotlin Hello World template\u003c/p\u003e\n",
      "command": "hello.kt@jbangdev/jbang~src/main/resources",
      "fullcommand": "jbang init -t hello.kt@jbangdev/jbang~src/main/resources",
      "link": "https://github.com/jbangdev/jbang/blob/d863c332d0ff207ef3a88039e701cda09cc54302/src/main/resources/jbang-catalog.json"
    },
    {
      "stars": 1357,
      "icon_url": "https://avatars.githubusercontent.com/u/60074102?v\u003d4",
      "repoOwner": "jbangdev",
      "repoName": "jbang",
      "alias": "hello.groovy",
      "description": "\u003cp\u003eBasic groovy Hello World template\u003c/p\u003e\n",
      "command": "hello.groovy@jbangdev/jbang~src/main/resources",
      "fullcommand": "jbang init -t hello.groovy@jbangdev/jbang~src/main/resources",
      "link": "https://github.com/jbangdev/jbang/blob/d863c332d0ff207ef3a88039e701cda09cc54302/src/main/resources/jbang-catalog.json"
    },
    {
      "stars": 1357,
      "icon_url": "https://avatars.githubusercontent.com/u/60074102?v\u003d4",
      "repoOwner": "jbangdev",
      "repoName": "jbang",
      "alias": "readme.md",
      "description": "\u003cp\u003eBasic markdown readme template\u003c/p\u003e\n",
      "command": "readme.md@jbangdev/jbang~src/main/resources",
      "fullcommand": "jbang init -t readme.md@jbangdev/jbang~src/main/resources",
      "link": "https://github.com/jbangdev/jbang/blob/d863c332d0ff207ef3a88039e701cda09cc54302/src/main/resources/jbang-catalog.json"
    },
    {
      "stars": 1357,
      "icon_url": "https://avatars.githubusercontent.com/u/60074102?v\u003d4",
      "repoOwner": "jbangdev",
      "repoName": "jbang",
      "alias": "qcli",
      "description": "\u003cp\u003eQuarkus CLI template\u003c/p\u003e\n",
      "command": "qcli@jbangdev/jbang~src/main/resources",
      "fullcommand": "jbang init -t qcli@jbangdev/jbang~src/main/resources",
      "link": "https://github.com/jbangdev/jbang/blob/d863c332d0ff207ef3a88039e701cda09cc54302/src/main/resources/jbang-catalog.json"
    },
    {
      "stars": 1357,
      "icon_url": "https://avatars.githubusercontent.com/u/60074102?v\u003d4",
      "repoOwner": "jbangdev",
      "repoName": "jbang",
      "alias": "qmetrics",
      "description": "\u003cp\u003eQuarkus Metrics template\u003c/p\u003e\n",
      "command": "qmetrics@jbangdev/jbang~src/main/resources",
      "fullcommand": "jbang init -t qmetrics@jbangdev/jbang~src/main/resources",
      "link": "https://github.com/jbangdev/jbang/blob/d863c332d0ff207ef3a88039e701cda09cc54302/src/main/resources/jbang-catalog.json"
    },
    {
      "stars": 1357,
      "icon_url": "https://avatars.githubusercontent.com/u/60074102?v\u003d4",
      "repoOwner": "jbangdev",
      "repoName": "jbang",
      "alias": "qrest",
      "description": "\u003cp\u003eQuarkus REST template\u003c/p\u003e\n",
      "command": "qrest@jbangdev/jbang~src/main/resources",
      "fullcommand": "jbang init -t qrest@jbangdev/jbang~src/main/resources",
      "link": "https://github.com/jbangdev/jbang/blob/d863c332d0ff207ef3a88039e701cda09cc54302/src/main/resources/jbang-catalog.json"
    },
    {
      "stars": 2,
      "icon_url": "https://avatars.githubusercontent.com/u/46711?v\u003d4",
      "repoOwner": "linux-china",
      "repoName": "jbang-spring-boot",
      "alias": "SpringBoot2",
      "description": "\u003cp\u003eSpring Boot 2 Java App Template\u003c/p\u003e\n",
      "command": "SpringBoot2@linux-china/jbang-spring-boot",
      "fullcommand": "jbang init -t SpringBoot2@linux-china/jbang-spring-boot",
      "link": "https://github.com/linux-china/jbang-spring-boot/blob/cc36d6a2a8d68868eb8aa2ae5ee0e81f797d0fd1/jbang-catalog.json"
    },
    {
      "stars": 2,
      "icon_url": "https://avatars.githubusercontent.com/u/46711?v\u003d4",
      "repoOwner": "linux-china",
      "repoName": "jbang-spring-boot",
      "alias": "SpringBoot3",
      "description": "\u003cp\u003eSpring Boot 3 Java App Template\u003c/p\u003e\n",
      "command": "SpringBoot3@linux-china/jbang-spring-boot",
      "fullcommand": "jbang init -t SpringBoot3@linux-china/jbang-spring-boot",
      "link": "https://github.com/linux-china/jbang-spring-boot/blob/cc36d6a2a8d68868eb8aa2ae5ee0e81f797d0fd1/jbang-catalog.json"
    },
    {
      "stars": 2,
      "icon_url": "https://avatars.githubusercontent.com/u/46711?v\u003d4",
      "repoOwner": "linux-china",
      "repoName": "jbang-spring-boot",
      "alias": "SpringBoot2Kt",
      "description": "\u003cp\u003eSpring Boot 2 Kotlin App Template\u003c/p\u003e\n",
      "command": "SpringBoot2Kt@linux-china/jbang-spring-boot",
      "fullcommand": "jbang init -t SpringBoot2Kt@linux-china/jbang-spring-boot",
      "link": "https://github.com/linux-china/jbang-spring-boot/blob/cc36d6a2a8d68868eb8aa2ae5ee0e81f797d0fd1/jbang-catalog.json"
    },
    {
      "stars": 2,
      "icon_url": "https://avatars.githubusercontent.com/u/46711?v\u003d4",
      "repoOwner": "linux-china",
      "repoName": "jbang-spring-boot",
      "alias": "SpringBoot3Kt",
      "description": "\u003cp\u003eSpring Boot 3 Kotlin App Template\u003c/p\u003e\n",
      "command": "SpringBoot3Kt@linux-china/jbang-spring-boot",
      "fullcommand": "jbang init -t SpringBoot3Kt@linux-china/jbang-spring-boot",
      "link": "https://github.com/linux-china/jbang-spring-boot/blob/cc36d6a2a8d68868eb8aa2ae5ee0e81f797d0fd1/jbang-catalog.json"
    },
    {
      "stars": 0,
      "icon_url": "https://avatars.githubusercontent.com/u/27719?v\u003d4",
      "repoOwner": "jianglibo",
      "repoName": "jbang-catalog",
      "alias": "github",
      "description": "\u003cp\u003eSimple cli to querying github\u003c/p\u003e\n",
      "command": "github@jianglibo",
      "fullcommand": "jbang init -t github@jianglibo",
      "link": "https://github.com/jianglibo/jbang-catalog/blob/9ea753070a3e4713a55a3f9bd63e86a9b67b9447/jbang-catalog.json"
    }
  ],
  "templateCount": 17
}